{
  "format_version": "3.0",
  "exporter": "bind_exporter",
  "version": "0.8.0",
  "category": "Network",
  "description": "Prometheus exporter for Bind (DNS) statistics",
  "last_updated": "2026-03-02T04:43:14.391294+00:00",
  "artifacts": {
    "rpm": {
      "el8": {
        "amd64": {
          "status": "success",
          "url": "https://github.com/sckyzo/monitoring-hub/releases/latest/download/bind_exporter-0.8.0-1.el8.x86_64.rpm",
          "size_bytes": 4262536,
          "sha256": "ae34ff3e2066be7271c3cf78f83643ff17979c7f9d21bd4e11ca5913b5ebc5e8",
          "build_date": "2026-03-02T04:37:23.446789+00:00"
        },
        "arm64": {
          "status": "success",
          "url": "https://github.com/sckyzo/monitoring-hub/releases/latest/download/bind_exporter-0.8.0-1.el8.aarch64.rpm",
          "size_bytes": 3708712,
          "sha256": "6d016a5ab54ee3a5dad9118401e22068bfa1fc808b7609f65b8f5a2d13afc1bf",
          "build_date": "2026-03-02T04:37:39.173381+00:00"
        }
      },
      "el10": {
        "arm64": {
          "status": "success",
          "url": "https://github.com/sckyzo/monitoring-hub/releases/latest/download/bind_exporter-0.8.0-1.el10.aarch64.rpm",
          "size_bytes": 3746452,
          "sha256": "e3c866416fe5c2ee801ccc637e1c6941634ddbf1797206b9d380fc1b4c26084f",
          "build_date": "2026-03-02T04:33:14.327338+00:00"
        },
        "amd64": {
          "status": "success",
          "url": "https://github.com/sckyzo/monitoring-hub/releases/latest/download/bind_exporter-0.8.0-1.el10.x86_64.rpm",
          "size_bytes": 4159435,
          "sha256": "1f4aa62489eb08a478edfe65224cba13b0bd06b0cc4b0ad6563cc083fd588ee9",
          "build_date": "2026-03-02T04:37:40.716172+00:00"
        }
      },
      "el9": {
        "arm64": {
          "status": "success",
          "url": "https://github.com/sckyzo/monitoring-hub/releases/latest/download/bind_exporter-0.8.0-1.el9.aarch64.rpm",
          "size_bytes": 3746218,
          "sha256": "3b36f03734a62a9c977efa88806eb84b0d8da1e1f68d501e7894cacb15c23da4",
          "build_date": "2026-03-02T04:42:19.695808+00:00"
        },
        "amd64": {
          "status": "success",
          "url": "https://github.com/sckyzo/monitoring-hub/releases/latest/download/bind_exporter-0.8.0-1.el9.x86_64.rpm",
          "size_bytes": 4158692,
          "sha256": "a9a6ddf2299cc926672e2bede8ba6087ff90fe3845ec00c1ab61d1d3bdf10804",
          "build_date": "2026-03-02T04:43:14.391294+00:00"
        }
      }
    },
    "deb": {
      "debian-12": {
        "amd64": {
          "status": "success",
          "url": "https://github.com/sckyzo/monitoring-hub/releases/latest/download/bind-exporter_0.8.0-1_amd64.deb",
          "size_bytes": 9515606,
          "sha256": "5d25a3e983fb2e2c21efcdeb84a08372a3a4c5c3c8391d89f4eff86c0b042fe7",
          "build_date": "2026-03-02T04:21:14.843562+00:00"
        },
        "arm64": {
          "status": "success",
          "url": "https://github.com/sckyzo/monitoring-hub/releases/latest/download/bind-exporter_0.8.0-1_arm64.deb",
          "size_bytes": 8914882,
          "sha256": "8b19e6d5f2a4ea661e145653325b253cc211b69baa38354dd59ed7470c516533",
          "build_date": "2026-03-02T04:29:22.118240+00:00"
        }
      }
    },
    "docker": {
      "status": "success",
      "images": [
        {
          "registry": "ghcr.io",
          "repository": "SckyzO/monitoring-hub/bind_exporter",
          "tags": [
            "0.8.0",
            "latest"
          ],
          "architectures": [
            "linux/amd64"
          ],
          "created": "2026-03-02T04:18:52Z"
        }
      ],
      "build_date": "2026-03-02T04:18:52.286984+00:00"
    }
  },
  "status": {
    "rpm": "success",
    "deb": "success",
    "docker": "success"
  }
}