{
  "format_version": "3.0",
  "exporter": "apache_exporter",
  "version": "1.0.12",
  "category": "Web",
  "description": "Prometheus exporter for Apache HTTP Server",
  "last_updated": "2026-02-23T04:53:53.973659+00:00",
  "artifacts": {
    "rpm": {
      "el10": {
        "amd64": {
          "status": "success",
          "url": "https://github.com/sckyzo/monitoring-hub/releases/latest/download/apache_exporter-1.0.12-1.el10.x86_64.rpm",
          "size_bytes": 4178549,
          "sha256": "0499fdf29e993ef64f3cc567582ef217c73a478bc072ae3468b77cedad51ff64",
          "build_date": "2026-02-23T04:40:14.760399+00:00"
        },
        "arm64": {
          "status": "success",
          "url": "https://github.com/sckyzo/monitoring-hub/releases/latest/download/apache_exporter-1.0.12-1.el10.aarch64.rpm",
          "size_bytes": 3724389,
          "sha256": "f5299bfddb4b8c1b6a454b4de2c3c094af380a8a18e6b6957dc58a58ffb3af77",
          "build_date": "2026-02-23T04:50:40.970346+00:00"
        }
      },
      "el8": {
        "arm64": {
          "status": "success",
          "url": "https://github.com/sckyzo/monitoring-hub/releases/latest/download/apache_exporter-1.0.12-1.el8.aarch64.rpm",
          "size_bytes": 3686144,
          "sha256": "f65936cad44cd37df3e3fc4223d9867d66000e59fde30b443ecbcdee605d3f8f",
          "build_date": "2026-02-23T04:53:53.973659+00:00"
        },
        "amd64": {
          "status": "success",
          "url": "https://github.com/sckyzo/monitoring-hub/releases/latest/download/apache_exporter-1.0.12-1.el8.x86_64.rpm",
          "size_bytes": 4282744,
          "sha256": "c829f69e2d26cfd5c54b8abccdf1dfc410824f3e8ac7399a5e75bf4ddbfc3e0d",
          "build_date": "2026-02-23T04:51:26.845654+00:00"
        }
      },
      "el9": {
        "amd64": {
          "status": "success",
          "url": "https://github.com/sckyzo/monitoring-hub/releases/latest/download/apache_exporter-1.0.12-1.el9.x86_64.rpm",
          "size_bytes": 4179713,
          "sha256": "53d9471afa3087b5d03e0a8c9541bad84c6480aa6cda7333b2175cea1630d27e",
          "build_date": "2026-02-23T04:44:47.528214+00:00"
        },
        "arm64": {
          "status": "success",
          "url": "https://github.com/sckyzo/monitoring-hub/releases/latest/download/apache_exporter-1.0.12-1.el9.aarch64.rpm",
          "size_bytes": 3724134,
          "sha256": "05ea2a95896d09b64003f6b2ced12351d7b3e861083d494f206fa8a659d94d70",
          "build_date": "2026-02-23T04:44:44.756356+00:00"
        }
      }
    },
    "deb": {
      "debian-12": {
        "amd64": {
          "status": "success",
          "url": "https://github.com/sckyzo/monitoring-hub/releases/latest/download/apache-exporter_1.0.12-1_amd64.deb",
          "size_bytes": 9255418,
          "sha256": "73f7cae03883ba7878cc9f32d2884b5ab8a0378d148bb1c92d952331645a1ca5",
          "build_date": "2026-02-23T04:31:35.472114+00:00"
        },
        "arm64": {
          "status": "success",
          "url": "https://github.com/sckyzo/monitoring-hub/releases/latest/download/apache-exporter_1.0.12-1_arm64.deb",
          "size_bytes": 8493550,
          "sha256": "927c505c35bbad1621efe624de355f688a6d8faeb915fb85abff0b99ba133e29",
          "build_date": "2026-02-23T04:38:02.561634+00:00"
        }
      }
    },
    "docker": {
      "status": "success",
      "images": [
        {
          "registry": "ghcr.io",
          "repository": "SckyzO/monitoring-hub/apache_exporter",
          "tags": [
            "1.0.12",
            "latest"
          ],
          "architectures": [
            "linux/amd64"
          ],
          "created": "2026-02-23T04:27:53Z"
        }
      ],
      "build_date": "2026-02-23T04:27:53.278251+00:00"
    }
  },
  "status": {
    "rpm": "success",
    "deb": "success",
    "docker": "success"
  }
}