{
  "format_version": "3.0",
  "exporter": "nats_exporter",
  "version": "0.19.1",
  "category": "Messaging",
  "description": "NATS metrics exporter for Prometheus.",
  "last_updated": "2026-03-16T05:22:11.525690+00:00",
  "artifacts": {
    "rpm": {
      "el8": {
        "amd64": {
          "status": "success",
          "url": "https://github.com/sckyzo/monitoring-hub/releases/latest/download/nats_exporter-0.19.1-1.el8.x86_64.rpm",
          "size_bytes": 3507444,
          "sha256": "eb34a8622c737ffee846a6c2cf8bc9fb03a76c219a47dcafa5bdc6f0672a81fa",
          "build_date": "2026-03-16T05:16:28.637623+00:00"
        },
        "arm64": {
          "status": "success",
          "url": "https://github.com/sckyzo/monitoring-hub/releases/latest/download/nats_exporter-0.19.1-1.el8.aarch64.rpm",
          "size_bytes": 2998704,
          "sha256": "21b9d7551b10a46c10083a0023418f6434d80c5e8ce65e8965f6193486487d78",
          "build_date": "2026-03-16T05:20:46.186205+00:00"
        }
      },
      "el10": {
        "arm64": {
          "status": "success",
          "url": "https://github.com/sckyzo/monitoring-hub/releases/latest/download/nats_exporter-0.19.1-1.el10.aarch64.rpm",
          "size_bytes": 3092510,
          "sha256": "fb8cb42f62efd13d0f703ac4819aab53f04f3b4204da011a5a1e2c601bc27a97",
          "build_date": "2026-03-16T05:19:49.804078+00:00"
        },
        "amd64": {
          "status": "success",
          "url": "https://github.com/sckyzo/monitoring-hub/releases/latest/download/nats_exporter-0.19.1-1.el10.x86_64.rpm",
          "size_bytes": 3468270,
          "sha256": "08205e186aa522d70e3d8914674c5fbfd0227172d69b021261cf79c3251206a5",
          "build_date": "2026-03-16T05:22:11.525690+00:00"
        }
      },
      "el9": {
        "arm64": {
          "status": "success",
          "url": "https://github.com/sckyzo/monitoring-hub/releases/latest/download/nats_exporter-0.19.1-1.el9.aarch64.rpm",
          "size_bytes": 3092367,
          "sha256": "712838d6c62326f4fb757f58ce3a88499364ac3347fac78ff8037d270631e096",
          "build_date": "2026-03-16T05:19:18.677565+00:00"
        },
        "amd64": {
          "status": "success",
          "url": "https://github.com/sckyzo/monitoring-hub/releases/latest/download/nats_exporter-0.19.1-1.el9.x86_64.rpm",
          "size_bytes": 3468243,
          "sha256": "2edc847fda8e682db077ae6a645892dad68466e4738aa6ca715c2eb063868322",
          "build_date": "2026-03-16T05:18:18.077493+00:00"
        }
      }
    },
    "deb": {
      "debian-12": {
        "amd64": {
          "status": "success",
          "url": "https://github.com/sckyzo/monitoring-hub/releases/latest/download/nats-exporter_0.19.1-1_amd64.deb",
          "size_bytes": 4106850,
          "sha256": "d7e0c690944203043172373a5e6e205bb25ba328fad55689121bafa023d21e5f",
          "build_date": "2026-03-16T04:53:49.443548+00:00"
        },
        "arm64": {
          "status": "success",
          "url": "https://github.com/sckyzo/monitoring-hub/releases/latest/download/nats-exporter_0.19.1-1_arm64.deb",
          "size_bytes": 3708572,
          "sha256": "57fe888c43be88c35c14eff9782ebe889296efe79ab40a277f5a1838b488b86c",
          "build_date": "2026-03-16T04:55:45.936519+00:00"
        }
      }
    },
    "docker": {
      "status": "success",
      "images": [
        {
          "registry": "ghcr.io",
          "repository": "SckyzO/monitoring-hub/nats_exporter",
          "tags": [
            "0.19.1",
            "latest"
          ],
          "architectures": [
            "linux/amd64"
          ],
          "created": "2026-03-16T04:44:12Z"
        }
      ],
      "build_date": "2026-03-16T04:44:12.349267+00:00"
    }
  },
  "status": {
    "rpm": "success",
    "deb": "success",
    "docker": "success"
  }
}